{
    "format_version": 1.0,

    "timestamp": "2022-10-12T18:00:00.000Z",
    "operation_uuid": "0f657b36-4b0f-4a2d-9c2e-1dcd615e7d8c",
    "mode": "Replica",

    "cluster": {
        "cluster_id": "docker_compose",
        "name": "docker_compose_test",
        "state": "restarted",
        "roles": [
            {
                "name": "cloud_admin",
                "encrypted_password": "b093c0d3b281ba6da1eacc608620abd8",
                "options": null
            }
        ],
        "databases": [
        ],
        "settings": [
            {
                "name": "fsync",
                "value": "off",
                "vartype": "bool"
            },
            {
                "name": "wal_level",
                "value": "replica",
                "vartype": "enum"
            },
            {
                "name": "wal_log_hints",
                "value": "off",
                "vartype": "bool"
            },
            {
                "name": "port",
                "value": "55433",
                "vartype": "integer"
            },
            {
                "name": "shared_buffers",
                "value": "1MB",
                "vartype": "string"
            },
            {
                "name": "max_connections",
                "value": "100",
                "vartype": "integer"
            },
            {
                "name": "listen_addresses",
                "value": "0.0.0.0",
                "vartype": "string"
            },
            {
                "name": "max_wal_senders",
                "value": "10",
                "vartype": "integer"
            },
            {
                "name": "max_replication_slots",
                "value": "10",
                "vartype": "integer"
            },
            {
                "name": "wal_sender_timeout",
                "value": "5s",
                "vartype": "string"
            },
            {
                "name": "wal_keep_size",
                "value": "0",
                "vartype": "integer"
            },
            {
                "name": "restart_after_crash",
                "value": "off",
                "vartype": "bool"
            },
            {
                "name": "shared_preload_libraries",
                "value": "neon",
                "vartype": "string"
            },
            {
                "name": "neon.timeline_id",
                "value": "TIMELINE_ID",
                "vartype": "string"
            },
            {
                "name": "neon.tenant_id",
                "value": "TENANT_ID",
                "vartype": "string"
            },
            {
                "name": "neon.pageserver_connstring",
                "value": "host=ipc-service port=6400",
                "vartype": "string"
            },
	    {
                "name": "hot_standby",
                "value": "on",
                "vartype": "bool"
            },
            {
                "name": "primary_conninfo",
                "value": "host=ipc-service port=5454 options='-c timeline_id=TIMELINE_ID tenant_id=TENANT_ID' application_name=replica replication=true",
                "vartype": "string"
            },
            {
                "name": "primary_slot_name",
                "value": "repl_TIMELINE_ID_",
                "vartype": "string"
            }
        ]
    },

    "delta_operations": [
    ]
}
